py_commit_checker/__init__.py
py_commit_checker/__version__.py
py_commit_checker/py_commit_checker.py
py_commit_checker-0.3.1.data/scripts/py-commit-checker-branch
py_commit_checker-0.3.1.dist-info/LICENSE
py_commit_checker-0.3.1.dist-info/METADATA
py_commit_checker-0.3.1.dist-info/WHEEL
py_commit_checker-0.3.1.dist-info/entry_points.txt
py_commit_checker-0.3.1.dist-info/top_level.txt
py_commit_checker-0.3.1.dist-info/RECORD
