Metadata-Version: 2.1
Name: py-commit-checker
Version: 0.3.1
Summary: Basic commit checker, with optional emoji check
Home-page: https://github.com/noahp/py-commit-checker
Author: Noah Pendleton
Author-email: 2538614+noahp@users.noreply.github.com
License: MIT
Project-URL: Code, https://github.com/noahp/py-commit-checker
Project-URL: Issue tracker, https://github.com/noahp/py-commit-checker/issues
Platform: UNKNOWN
Classifier: License :: OSI Approved :: MIT License
Classifier: Programming Language :: Python :: 2.7
Classifier: Programming Language :: Python :: 3.7
Classifier: Programming Language :: Python :: 3.8
Classifier: Operating System :: OS Independent
Requires-Dist: click (>=6.5)
Requires-Dist: emoji (==1.2.*)
Requires-Dist: gitpython (>=2.1.11)
